requests_curl/__init__.py
requests_curl/adapter.py
requests_curl/error.py
requests_curl/pool.py
requests_curl/pool_provider.py
requests_curl/request.py
requests_curl/response.py
requests_curl_antitls-0.1.0rc3.dist-info/METADATA
requests_curl_antitls-0.1.0rc3.dist-info/WHEEL
requests_curl_antitls-0.1.0rc3.dist-info/top_level.txt
requests_curl_antitls-0.1.0rc3.dist-info/RECORD
