Metadata-Version: 2.1
Name: requests-curl-antitls
Version: 0.1.0rc3
Summary: the requests package which passed ja3
Home-page: https://github.com/ycq0125/pycurl
Author: spike
Author-email: 2466857975@qq.com
Maintainer: synodriver
License: GPLv3
Keywords: requests,curl,antitls
Platform: UNKNOWN
Classifier: Development Status :: 3 - Alpha
Classifier: Operating System :: POSIX
Classifier: License :: OSI Approved :: GNU General Public License v3 (GPLv3)
Classifier: Programming Language :: Python
Classifier: Programming Language :: Python :: 3.6
Classifier: Programming Language :: Python :: 3.7
Classifier: Programming Language :: Python :: 3.8
Classifier: Programming Language :: Python :: 3.9
Classifier: Programming Language :: Python :: 3.10
Classifier: Programming Language :: Python :: Implementation :: CPython
Requires-Python: >=3.6
Requires-Dist: requests
Requires-Dist: pycurl-antitls (>=7.45.3rc1)
